<!DOCTYPE webpage SYSTEM "schema/dtd/website.dtd" [
<!NOTATION XML SYSTEM "xml">
<!ENTITY software_about SYSTEM "software_about.xml" NDATA XML>
]>

<webpage id="software">
<config param="desc" value="Software page"/>
<config param="rcsdate" value="$Date$"/>
<head>
<title
>Software</title>
<summary
>Introduction</summary>
<keywords
>Norman Walsh, DSSSL, SGML, XML, DocBook, Website</keywords>
</head>

<section
><title
>Willkommen zum BibleTime Projekt!</title>
<mediaobject
> <imageobject
> <imagedata fileref="/images/startuplogo.png" format="PNG"/> </imageobject
> <textobject
> <phrase
>startup logo</phrase
> </textobject
> </mediaobject>
<para
> BibleTime ist ein Bibelstudienprogramm für Linux. Wir denken, dass BibleTime ein nützliches Werkzeug für jeden Christen ist, der Linux benutzt. </para>

<para
> Wenn Sie mehr über BibleTime wissen möchten, lesen Sie bitte die "Über BibleTime"  Seiten: <olink targetdocent="software_about"
>Über BibleTime</olink
> </para>

</section>

</webpage>

