<!DOCTYPE webpage SYSTEM "schema/dtd/website.dtd" [
<!NOTATION XML SYSTEM "xml">
<!ENTITY software_about SYSTEM "software_about.xml" NDATA XML>
]>

<webpage id="software">
<config param="desc" value="Software page"/>
<config param="rcsdate" value="$Date$"/>
<head>
<title
>Software</title>
<summary
>Introduction</summary>
<keywords
>Norman Walsh, DSSSL, SGML, XML, DocBook, Website</keywords>
</head>

<section
><title
>Bem vindo(a) ao projeto BibleTime!</title>
<para
>  </para>
</section>

<section
><title
>#-#-#-#-#  software.po (PACKAGE VERSION)  #-#-#-#-#
#-#-#-#-#  software_news.po (PACKAGE VERSION)  #-#-#-#-#
Sobre o BibleTime</title>
	<formalpara
><title
></title>
		<para
>  </para>
	</formalpara>

	<formalpara
><title
></title>
		<para
>  </para>
		<para
>  </para>
	</formalpara>

	<formalpara
><title
></title>
		<para
>  </para>
		<para
>  </para>
	</formalpara>
</section>

</webpage>

