<!DOCTYPE webpage SYSTEM "../schema/dtd/website.dtd" [
<!NOTATION XML SYSTEM "xml">
]>

<webpage id="documentation_installation_sword">
<config param="desc" value="Sword's installation"/>
<config param="rcsdate" value="$Date$"/>
<head>
<title
>스워드(Sword)</title>
<summary
>How to install Swors</summary>
<keywords
>BibleTime, Sword, Installation, Modules, Help</keywords>
</head>

<section
><title
>스워드(Sword) 설치</title>
<para
> 이 페이지는 바이블타임에서 사용하는 스워드(Sword) 라이브러리를 설치하는 방법을 설명하고 있습니다. </para>

<para
> 스워드(Sword) 라이브러리의 설치는 바이블타임을 소스로부터 직접 설치할 경우에만 필요합니다! 바이너리 패키지를 이용하여 설치하신다면 스워드(Sword) 소스를 설치하실 필요가 없습니다. 바이블타임의 바이너리 패키지안에 포함되어 있습니다. </para>


<section
><title
>설치 과정</title>
<para
> 기본 설치 과정은 Crosswire Bible Society의 페이지에 설명이 되어 있습니다: </para>

<para
> <ulink url="http://www.crosswire.org/sword/software/index.jsp"
>http://www.crosswire.org/sword/software/index.jsp</ulink
> </para>
</section>

</section>

</webpage>

<!--
Local variables:
mode: docbook
End:
-->

