<!DOCTYPE webpage SYSTEM "../schema/dtd/website.dtd" [
<!NOTATION XML SYSTEM "xml">
]>

<webpage id="software_linkus">
<config param="desc" value="Link to us"
></config>
<config param="rcsdate" value="$Date$"
></config>
<head>
	<title
>Liens vers nous</title>
	<summary
>How to link to www.bibletime.info</summary>
	<keywords
>BibleTime, Linux, Software, biblestudy, bible study, KDE, God, Religion, Bible, devotional, crosswire, sword, links, link us</keywords>
</head>

<section
><title
>Comment créer un lien sur mon site vers www.bibletime.info ?</title>
<para
>Veuillez NE PAS copier les images car leur design pourrait évoluer avec le temps. </para>

<section
><title
>Grande bannière</title>
<para
>Insérez le code HTML suivant sur vos pages : <programlisting>
<![CDATA[
 <a href="http://www.bibletime.info/" target="_blank">
 <img src="http://www.bibletime.info/images/banner/big.jpg" width="312" height="60" border="0"/>
 </a>
]]>
</programlisting
> This will look like this: <ulink url="http://www.bibletime.info/"
> <mediaobject
> <imageobject
> <imagedata fileref="/images/banner/big.jpg" format="JPG"/> </imageobject
> </mediaobject
> </ulink
> </para>
</section>

<section
><title
>Petite bannière</title>
<para
>Insérez le code HTML suivant sur vos pages : <programlisting>
<![CDATA[
 <a href="http://www.bibletime.info/" target="_blank">
 <img src="http://www.bibletime.info/images/banner/small.jpg" width="88" height="31" border="0"/>
 </a>
]]>
</programlisting
> This will look like this: <ulink url="http://www.bibletime.info/"
> <mediaobject
> <imageobject
> <imagedata fileref="/images/banner/small.jpg" format="JPG"/> </imageobject
> </mediaobject
> </ulink
> </para>
</section>


<section
><title
>Lien textuel</title>
<para
>Pour insérer un lien textuel, veuillez insérez le code HTML suivant sur vos pages : <programlisting>
<![CDATA[
 <a href="http://www.bibletime.info/" TARGET="_blank">
 BibleTime - Bible study software for KDE
 </a>
]]>
</programlisting
> This will look like this: <ulink url="http://www.bibletime.info/"
>BibleTime - Bible study software for KDE</ulink
> </para>
</section>

</section>
</webpage>
